{"info":{"start":"2025-07-28T08:52:59.995Z","end":"2025-07-28T08:53:02.654Z","_duration":2659,"type":"runner","cid":"0-1","capabilities":{"acceptInsecureCerts":false,"browserName":"firefox","browserVersion":"143.0a1","moz:accessibilityChecks":false,"moz:buildID":"20250727211203","moz:geckodriverVersion":"0.36.0","moz:headless":true,"moz:platformVersion":"10.0","moz:processID":27912,"moz:profile":"C:\\Users\\misha\\AppData\\Local\\Temp\\rust_mozprofiler9029f","moz:shutdownTimeout":60000,"moz:webdriverClick":true,"moz:windowless":false,"pageLoadStrategy":"normal","platformName":"windows","proxy":{},"setWindowRect":true,"strictFileInteractability":false,"timeouts":{"implicit":0,"pageLoad":300000,"script":30000},"unhandledPromptBehavior":"ignore","userAgent":"Mozilla/5.0 (Windows NT 10.0; Win64; x64; rv:143.0) Gecko/20100101 Firefox/143.0","webSocketUrl":"ws://127.0.0.1:49251/session/c8c7d7a2-a2e0-4bdb-a87e-b5b7d8c1364c","wdio:driverPID":11044,"sessionId":"c8c7d7a2-a2e0-4bdb-a87e-b5b7d8c1364c"},"sanitizedCapabilities":"firefox.143_0a1.windows","config":{"protocol":"http","hostname":"localhost","path":"/","capabilities":{"browserName":"firefox","moz:firefoxOptions":{"binary":"C:\\Users\\misha\\AppData\\Local\\Temp\\firefox\\win64-nightly_143.0a1\\firefox\\firefox.exe","args":["-headless"]},"webSocketUrl":true,"unhandledPromptBehavior":"ignore"},"logLevel":"error","connectionRetryTimeout":120000,"connectionRetryCount":3,"logLevels":{},"enableDirectConnect":true,"strictSSL":true,"port":49223,"requestedCapabilities":{"browserName":"firefox","moz:firefoxOptions":{"binary":"C:\\Users\\misha\\AppData\\Local\\Temp\\firefox\\win64-nightly_143.0a1\\firefox\\firefox.exe","args":["-headless"]}},"automationProtocol":"webdriver","waitforInterval":100,"waitforTimeout":5000,"onReload":[],"beforeCommand":[],"afterCommand":[],"rootDir":"C:\\Users\\Public\\Studying\\Automated_Testing_in_JavaScript\\WDIO_Lab_task\\configs","specs":["../test/specs/**/*.js"],"suites":{},"exclude":[],"groupLogsByTestSpec":false,"excludeDriverLogs":[],"bail":0,"framework":"mocha","reporters":["spec",["html-nice",{"outputDir":"./reports/html-reports","filename":"report.html","reportTitle":"WDIO HTML Report"}]],"services":[],"maxInstances":2,"maxInstancesPerCapability":100,"injectGlobals":true,"filesToWatch":[],"execArgv":[],"runnerEnv":{},"runner":"local","shard":{"current":1,"total":1},"specFileRetries":0,"specFileRetriesDelay":0,"specFileRetriesDeferred":false,"autoAssertOnTestEnd":true,"reporterSyncInterval":100,"reporterSyncTimeout":5000,"cucumberFeaturesWithLineNumbers":[],"mochaOpts":{"timeout":60000,"ui":"bdd"},"jasmineOpts":{"defaultTimeoutInterval":10000},"cucumberOpts":{"timeout":10000},"onPrepare":[],"onWorkerStart":[],"onWorkerEnd":[],"before":[],"beforeSession":[],"beforeSuite":[],"beforeHook":[],"beforeTest":[null,null],"afterTest":[null],"afterHook":[],"afterSuite":[],"afterSession":[],"after":[null],"onComplete":[],"beforeAssertion":[],"afterAssertion":[],"beforeFeature":[],"beforeScenario":[],"beforeStep":[null,null],"afterStep":[null],"afterScenario":[],"afterFeature":[],"_":["run","run"],"$0":"node_modules\\@wdio\\cli\\bin\\wdio.js","config-path":"./configs/wdio.firefox.conf.js","ignoredWorkerServices":[]},"specs":["file:///C:/Users/Public/Studying/Automated_Testing_in_JavaScript/WDIO_Lab_task/test/specs/signUpIn.spec.js"],"sessionId":"c8c7d7a2-a2e0-4bdb-a87e-b5b7d8c1364c","isMultiremote":false,"instanceOptions":{"c8c7d7a2-a2e0-4bdb-a87e-b5b7d8c1364c":{"protocol":"http","hostname":"localhost","path":"/","capabilities":{"browserName":"firefox","moz:firefoxOptions":{"binary":"C:\\Users\\misha\\AppData\\Local\\Temp\\firefox\\win64-nightly_143.0a1\\firefox\\firefox.exe","args":["-headless"]},"webSocketUrl":true,"unhandledPromptBehavior":"ignore"},"logLevel":"error","connectionRetryTimeout":120000,"connectionRetryCount":3,"logLevels":{},"enableDirectConnect":true,"strictSSL":true,"port":49223,"requestedCapabilities":{"browserName":"firefox","moz:firefoxOptions":{"binary":"C:\\Users\\misha\\AppData\\Local\\Temp\\firefox\\win64-nightly_143.0a1\\firefox\\firefox.exe","args":["-headless"]}},"automationProtocol":"webdriver","waitforInterval":100,"waitforTimeout":5000,"onReload":[],"beforeCommand":[],"afterCommand":[],"rootDir":"C:\\Users\\Public\\Studying\\Automated_Testing_in_JavaScript\\WDIO_Lab_task\\configs","specs":["../test/specs/**/*.js"],"suites":{},"exclude":[],"groupLogsByTestSpec":false,"excludeDriverLogs":[],"bail":0,"framework":"mocha","reporters":["spec",["html-nice",{"outputDir":"./reports/html-reports","filename":"report.html","reportTitle":"WDIO HTML Report"}]],"services":[],"maxInstances":2,"maxInstancesPerCapability":100,"injectGlobals":true,"filesToWatch":[],"execArgv":[],"runnerEnv":{},"runner":"local","shard":{"current":1,"total":1},"specFileRetries":0,"specFileRetriesDelay":0,"specFileRetriesDeferred":false,"autoAssertOnTestEnd":true,"reporterSyncInterval":100,"reporterSyncTimeout":5000,"cucumberFeaturesWithLineNumbers":[],"mochaOpts":{"timeout":60000,"ui":"bdd"},"jasmineOpts":{"defaultTimeoutInterval":10000},"cucumberOpts":{"timeout":10000},"onPrepare":[],"onWorkerStart":[],"onWorkerEnd":[],"before":[],"beforeSession":[],"beforeSuite":[],"beforeHook":[],"beforeTest":[null,null],"afterTest":[null],"afterHook":[],"afterSuite":[],"afterSession":[],"after":[null],"onComplete":[],"beforeAssertion":[],"afterAssertion":[],"beforeFeature":[],"beforeScenario":[],"beforeStep":[null,null],"afterStep":[null],"afterScenario":[],"afterFeature":[],"_":["run","run"],"$0":"node_modules\\@wdio\\cli\\bin\\wdio.js","config-path":"./configs/wdio.firefox.conf.js","ignoredWorkerServices":[]}},"retry":0,"failures":0,"retries":0},"metrics":{"passed":3,"skipped":0,"failed":0,"duration":2659,"start":"2025-07-28T08:52:59.996Z","end":"2025-07-28T08:53:02Z"},"title":"WDIO HTML Report","suites":[{"start":"2025-07-28T08:53:00.002Z","end":"2025-07-28T08:53:01.908Z","_duration":1906,"type":"suite:start","uid":"suite-0-0","cid":"0-1","file":"C:\\Users\\Public\\Studying\\Automated_Testing_in_JavaScript\\WDIO_Lab_task\\test\\specs\\signUpIn.spec.js","title":"Sign Up/In Page Tests","fullTitle":"Sign Up/In Page Tests","tests":[{"start":"2025-07-28T08:53:00.609Z","end":"2025-07-28T08:53:01.588Z","_duration":979,"type":"test","uid":"test-00-0","cid":"0-1","title":"should navigate to the sign up page and fill in the form","fullTitle":"Sign Up/In Page Tests.should navigate to the sign up page and fill in the form","output":[],"retries":0,"parent":"Sign Up/In Page Tests","state":"passed","body":"async () => {\r\n        await basePage.signInBtn.click();\r\n        await signUpPage.signUp();\r\n        expect(signInPage).isOpen = true;\r\n    }","events":[],"errorIndex":0},{"start":"2025-07-28T08:53:01.594Z","end":"2025-07-28T08:53:01.732Z","_duration":138,"type":"test","uid":"test-00-1","cid":"0-1","title":"should sign in with the registered account","fullTitle":"Sign Up/In Page Tests.should sign in with the registered account","output":[],"retries":0,"parent":"Sign Up/In Page Tests","state":"passed","body":"async () => {\r\n        await signInPage.signIn(testData.user.email, testData.user.password);\r\n        expect(userProfileInfo.signInCheck).toBeDisplayed();\r\n    }","events":[],"errorIndex":0},{"start":"2025-07-28T08:53:01.732Z","end":"2025-07-28T08:53:01.907Z","_duration":175,"type":"test","uid":"test-00-2","cid":"0-1","title":"should update user profile information","fullTitle":"Sign Up/In Page Tests.should update user profile information","output":[{"command":"getWindowHandle","method":"GET","endpoint":"/session/:sessionId/window","body":{},"result":{"error":{"url":"http://localhost:49223/session/c8c7d7a2-a2e0-4bdb-a87e-b5b7d8c1364c/window","opts":{"method":"GET","redirect":"follow","signal":{},"headers":{},"dispatcher":{"_events":{},"_eventsCount":0}},"code":"UND_ERR_CLOSED"}},"cid":"0-1","type":"result"}],"retries":0,"parent":"Sign Up/In Page Tests","state":"passed","body":"async () => {\r\n        await userProfileInfo.updateProfile(testData.update.firstName, testData.update.lastName);\r\n        const firstName = await userProfileInfo.firstNameInputField.getValue();\r\n        const lastName = await userProfileInfo.lastNameInputField.getValue();\r\n        firstName.should.be.a('string').and.equal('Johnas');\r\n        lastName.should.be.a('string').and.equal('Doele');\r\n    }","events":[],"errorIndex":0}],"hooks":[{"start":"2025-07-28T08:53:00.002Z","end":"2025-07-28T08:53:00.609Z","_duration":607,"type":"hook","uid":"hook-00-0","cid":"0-1","title":"\"before all\" hook for Sign Up/In Page Tests","parent":"Sign Up/In Page Tests","body":"async () => {\r\n        await basePage.open();\r\n        const title = await browser.getTitle();\r\n        assert.include(title, 'Practice Software Testing', 'Title does not match');\r\n        // title.should.be.a('string').and.equal('Practice Software Testing - Toolshop - v5.0');\r\n    }","errors":[],"currentTest":"should navigate to the sign up page and fill in the form"}],"suites":[],"parent":"","retries":0,"hooksAndTests":[{"start":"2025-07-28T08:53:00.002Z","end":"2025-07-28T08:53:00.609Z","_duration":607,"type":"hook","uid":"hook-00-0","cid":"0-1","title":"\"before all\" hook for Sign Up/In Page Tests","parent":"Sign Up/In Page Tests","body":"async () => {\r\n        await basePage.open();\r\n        const title = await browser.getTitle();\r\n        assert.include(title, 'Practice Software Testing', 'Title does not match');\r\n        // title.should.be.a('string').and.equal('Practice Software Testing - Toolshop - v5.0');\r\n    }","errors":[],"currentTest":"should navigate to the sign up page and fill in the form"},{"start":"2025-07-28T08:53:00.609Z","end":"2025-07-28T08:53:01.588Z","_duration":979,"type":"test","uid":"test-00-0","cid":"0-1","title":"should navigate to the sign up page and fill in the form","fullTitle":"Sign Up/In Page Tests.should navigate to the sign up page and fill in the form","output":[],"retries":0,"parent":"Sign Up/In Page Tests","state":"passed","body":"async () => {\r\n        await basePage.signInBtn.click();\r\n        await signUpPage.signUp();\r\n        expect(signInPage).isOpen = true;\r\n    }","events":[],"errorIndex":0},{"start":"2025-07-28T08:53:01.594Z","end":"2025-07-28T08:53:01.732Z","_duration":138,"type":"test","uid":"test-00-1","cid":"0-1","title":"should sign in with the registered account","fullTitle":"Sign Up/In Page Tests.should sign in with the registered account","output":[],"retries":0,"parent":"Sign Up/In Page Tests","state":"passed","body":"async () => {\r\n        await signInPage.signIn(testData.user.email, testData.user.password);\r\n        expect(userProfileInfo.signInCheck).toBeDisplayed();\r\n    }","events":[],"errorIndex":0},{"start":"2025-07-28T08:53:01.732Z","end":"2025-07-28T08:53:01.907Z","_duration":175,"type":"test","uid":"test-00-2","cid":"0-1","title":"should update user profile information","fullTitle":"Sign Up/In Page Tests.should update user profile information","output":[{"command":"getWindowHandle","method":"GET","endpoint":"/session/:sessionId/window","body":{},"result":{"error":{"url":"http://localhost:49223/session/c8c7d7a2-a2e0-4bdb-a87e-b5b7d8c1364c/window","opts":{"method":"GET","redirect":"follow","signal":{},"headers":{},"dispatcher":{"_events":{},"_eventsCount":0}},"code":"UND_ERR_CLOSED"}},"cid":"0-1","type":"result"}],"retries":0,"parent":"Sign Up/In Page Tests","state":"passed","body":"async () => {\r\n        await userProfileInfo.updateProfile(testData.update.firstName, testData.update.lastName);\r\n        const firstName = await userProfileInfo.firstNameInputField.getValue();\r\n        const lastName = await userProfileInfo.lastNameInputField.getValue();\r\n        firstName.should.be.a('string').and.equal('Johnas');\r\n        lastName.should.be.a('string').and.equal('Doele');\r\n    }","events":[],"errorIndex":0}]}],"reportFile":"C:\\Users\\Public\\Studying\\Automated_Testing_in_JavaScript\\WDIO_Lab_task\\reports\\html-reports\\report-0-1.html","browserName":"not specified"}